pytempscsp/__init__.py
pytempscsp/tempscsp.py
pytempscsp-0.9.4.dist-info/LICENSE.md
pytempscsp-0.9.4.dist-info/METADATA
pytempscsp-0.9.4.dist-info/WHEEL
pytempscsp-0.9.4.dist-info/RECORD
