Metadata-Version: 2.1
Name: pytempscsp
Version: 0.9.4
Summary: Temporal Scale-Space Toolbox for Python.
Home-page: https://github.com/tonylindeberg/pytempscsp
License: MIT
Author: Tony Lindeberg
Author-email: tony@kth.se
Requires-Python: >=3.7,<4.0
Classifier: License :: OSI Approved :: MIT License
Classifier: Programming Language :: Python :: 3
Classifier: Programming Language :: Python :: 3.7
Classifier: Programming Language :: Python :: 3.8
Classifier: Programming Language :: Python :: 3.9
Classifier: Programming Language :: Python :: 3.10
Classifier: Programming Language :: Python :: 3.11
Classifier: Programming Language :: Python :: 3.12
Requires-Dist: scipy (>=1.0.1,<2.0.0)
Project-URL: Repository, https://github.com/tonylindeberg/pytempscsp
